flexenvconfig/__init__.py
flexenvconfig-1.0.0.dist-info/LICENSE
flexenvconfig-1.0.0.dist-info/METADATA
flexenvconfig-1.0.0.dist-info/WHEEL
flexenvconfig-1.0.0.dist-info/RECORD
