Metadata-Version: 2.1
Name: flexenvconfig
Version: 1.0.0
Summary: An abstract configuration object used to facilitate building flexible configs from environment variables
Home-page: https://github.com/famazak/flexenvconfig
Author: famazak
Author-email: zakfama58@gmail.com
Requires-Python: >=3.11,<4.0
Classifier: Programming Language :: Python :: 3
Classifier: Programming Language :: Python :: 3.11
Classifier: Programming Language :: Python :: 3.12
Project-URL: Repository, https://github.com/famazak/flexenvconfig
